MANIFEST.in
README.md
setup.cfg
setup.py
landsat_theia.egg-info/PKG-INFO
landsat_theia.egg-info/SOURCES.txt
landsat_theia.egg-info/dependency_links.txt
landsat_theia.egg-info/requires.txt
landsat_theia.egg-info/top_level.txt
python/clipper_helper.py
python/general_helper.py
python/gs_helper.py
python/landsat_theia.py
python/search_helper.py