Metadata-Version: 1.1
Name: landsat-theia
Version: 0.0.2
Summary: A utility to search, download THEIA Landsat  satellite imagery
Home-page: https://github.com/yoannMoreau/landsat_theia
Author: Yoann M
Author-email: yoann.moreau@gmail.com
License: CCO
Platform: Posix;
Classifier: Development Status :: 3 - Alpha
